nskit/__init__.py
nskit/_logging.py
nskit/_version.py
nskit/common/__init__.py
nskit/common/extensions.py
nskit/common/lazy.py
nskit/common/configuration/__init__.py
nskit/common/configuration/mixins.py
nskit/common/configuration/sources.py
nskit/common/contextmanagers/__init__.py
nskit/common/contextmanagers/chdir.py
nskit/common/contextmanagers/env.py
nskit/common/contextmanagers/test_extensions.py
nskit/common/io/__init__.py
nskit/common/io/json.py
nskit/common/io/toml.py
nskit/common/io/yaml.py
nskit/common/logging/__init__.py
nskit/common/logging/config.py
nskit/common/logging/formatter.py
nskit/common/logging/library.py
nskit/common/logging/logger.py
nskit/mixer/__init__.py
nskit/mixer/repo.py
nskit/mixer/utilities.py
nskit/mixer/components/__init__.py
nskit/mixer/components/file.py
nskit/mixer/components/filesystem_object.py
nskit/mixer/components/folder.py
nskit/mixer/components/hook.py
nskit/mixer/components/license_file.py
nskit/mixer/components/recipe.py
nskit/mixer/hooks/__init__.py
nskit/mixer/hooks/git.py
nskit/mixer/hooks/pre_commit.py
nskit/recipes/__init__.py
nskit/recipes/recipe.py
nskit/recipes/python/__init__.py
nskit/recipes/python/api.py
nskit/recipes/python/package.py
nskit/recipes/python/ingredients/__init__.py
nskit/recipes/python/ingredients/__init__.py.template
nskit/recipes/python/ingredients/gitignore.template
nskit/recipes/python/ingredients/noxfile.py.template
nskit/recipes/python/ingredients/pre-commit-config.yaml.template
nskit/recipes/python/ingredients/pyproject.toml.template
nskit/recipes/python/ingredients/readme.md.template
nskit/recipes/python/ingredients/api/__init__.py
nskit/recipes/python/ingredients/api/api.__init__.py.template
nskit/recipes/python/ingredients/api/api.base.py.template
nskit/recipes/python/ingredients/api/app.py.template
nskit/recipes/python/ingredients/api/auth.py.template
nskit/recipes/python/ingredients/api/pyproject.toml.template
nskit/recipes/python/ingredients/api/readme.md.template
nskit-0.1.2.dist-info/LICENSE
nskit-0.1.2.dist-info/METADATA
nskit-0.1.2.dist-info/WHEEL
nskit-0.1.2.dist-info/entry_points.txt
nskit-0.1.2.dist-info/top_level.txt
nskit-0.1.2.dist-info/RECORD
